coininfo/__init__.py
coininfo/info.py
coininfo_timmeichholz-0.1.1.dist-info/METADATA
coininfo_timmeichholz-0.1.1.dist-info/WHEEL
coininfo_timmeichholz-0.1.1.dist-info/top_level.txt
coininfo_timmeichholz-0.1.1.dist-info/RECORD
