Metadata-Version: 2.1
Name: coininfo-timmeichholz
Version: 0.1.1
Requires-Dist: requests ==2.31.0
